g2w/__init__.py
g2w/__main__.py
g2w/api.py
g2w/gitlab.py
g2w/grafana.py
g2w/log.py
g2w/version.py
g2w/ws.py
g2w-0.3.0.dist-info/METADATA
g2w-0.3.0.dist-info/WHEEL
g2w-0.3.0.dist-info/entry_points.txt
g2w-0.3.0.dist-info/top_level.txt
g2w-0.3.0.dist-info/RECORD
