Metadata-Version: 2.1
Name: g2w
Version: 0.3.0
Summary: Gateway to notify Worksection tasks about events from Grafana, Gitlab (e.g commits)
Home-page: https://github.com/dgroup/g2w/
Author: lazylead
License: UNKNOWN
Platform: UNKNOWN
Requires-Dist: requests
Requires-Dist: requests-mock
Requires-Dist: types-requests
Requires-Dist: pytest
Requires-Dist: fastapi
Requires-Dist: uvicorn[standard]
Requires-Dist: pydantic
Requires-Dist: Airspeed
Requires-Dist: types-PyYAML
Requires-Dist: prometheus-fastapi-instrumentator
Provides-Extra: test
Requires-Dist: pytest ; extra == 'test'
Requires-Dist: coverage ; extra == 'test'
Requires-Dist: flake8 ; extra == 'test'
Requires-Dist: black ; extra == 'test'
Requires-Dist: isort ; extra == 'test'
Requires-Dist: pytest-cov ; extra == 'test'
Requires-Dist: codecov ; extra == 'test'
Requires-Dist: mypy ; extra == 'test'
Requires-Dist: gitchangelog ; extra == 'test'
Requires-Dist: mkdocs ; extra == 'test'
Requires-Dist: requests ; extra == 'test'
Requires-Dist: prometheus-fastapi-instrumentator ; extra == 'test'
